rivers_datasets_aggregation/__init__.py
rivers_datasets_aggregation/common/__init__.py
rivers_datasets_aggregation/common/linestring_query_grid.py
rivers_datasets_aggregation/common/progress.py
rivers_datasets_aggregation/examples/__init__.py
rivers_datasets_aggregation/examples/africa_grdc_stations_merit_elevations.py
rivers_datasets_aggregation/examples/africa_grdc_stations_on_frasson_geomorpho_database.py
rivers_datasets_aggregation/examples/africa_grdc_stations_on_merit_hydrobasins.py
rivers_datasets_aggregation/examples/frasson_geomorpho_database_statistics.py
rivers_datasets_aggregation/rasters/__init__.py
rivers_datasets_aggregation/rasters/copernicus_lc.py
rivers_datasets_aggregation/rasters/egm2008.py
rivers_datasets_aggregation/rasters/generic_rasters_collection.py
rivers_datasets_aggregation/rasters/merit_hydro_collection.py
rivers_datasets_aggregation/rasters/rasters_collection.py
rivers_datasets_aggregation/rasters/soilgrids_2017.py
rivers_datasets_aggregation/rivers_network/__init__.py
rivers_datasets_aggregation/rivers_network/stations_on_rivers_network.py
rivers_datasets_aggregation/utils/__init__.py
rivers_datasets_aggregation/utils/convert_geo_format.py
rivers_datasets_aggregation/vectors/__init__.py
rivers_datasets_aggregation/vectors/vectors_collection.py
tests/__init__.py
tests/test_soilgrids_aggregation.py
tests/data/GRDC_stations_AF.csv
tests/data/grdc_updated_data.shp
tests/data/ref/GRDC_stations_AF_clay_percentage.csv
rivers_datasets_aggregation-0.0.3.dist-info/LICENSE
rivers_datasets_aggregation-0.0.3.dist-info/METADATA
rivers_datasets_aggregation-0.0.3.dist-info/WHEEL
rivers_datasets_aggregation-0.0.3.dist-info/top_level.txt
rivers_datasets_aggregation-0.0.3.dist-info/RECORD
